litprinter/__init__.py
litprinter/box.py
litprinter/builtins.py
litprinter/coloring.py
litprinter/colors.py
litprinter/console.py
litprinter/core.py
litprinter/litprint.py
litprinter/panel.py
litprinter/segment.py
litprinter/style.py
litprinter/text.py
litprinter/traceback.py
litprinter/styles/__init__.py
litprinter/styles/autumn.py
litprinter/styles/base.py
litprinter/styles/custom.py
litprinter/styles/cyberpunk.py
litprinter/styles/dracula.py
litprinter/styles/forest.py
litprinter/styles/github.py
litprinter/styles/jarvis.py
litprinter/styles/material.py
litprinter/styles/modern.py
litprinter/styles/monochrome.py
litprinter/styles/monokai.py
litprinter/styles/neon.py
litprinter/styles/nord.py
litprinter/styles/ocean.py
litprinter/styles/retro.py
litprinter/styles/rich.py
litprinter/styles/solarized.py
litprinter/styles/sunset.py
litprinter/styles/synthwave.py
litprinter/styles/vscode.py
litprinter-0.3.2.data/data/litprinter_autoload.pth
litprinter-0.3.2.dist-info/licenses/LICENSE
litprinter-0.3.2.dist-info/METADATA
litprinter-0.3.2.dist-info/WHEEL
litprinter-0.3.2.dist-info/top_level.txt
litprinter-0.3.2.dist-info/RECORD
