Metadata-Version: 2.4
Name: litprinter
Version: 0.3.2
Summary: The most sophisticated debug printing library for Python - IceCream + Rich fusion with syntax highlighting and beautiful tracebacks
Author-email: OEvortex <helpingai5@gmail.com>
License-Expression: MIT
Project-URL: Homepage, https://github.com/OEvortex/litprinter
Project-URL: Bug Tracker, https://github.com/OEvortex/litprinter/issues
Project-URL: Documentation, https://github.com/OEvortex/litprinter#readme
Keywords: debug,print,icecream,rich,logging,traceback,formatting,syntax-highlighting
Classifier: Development Status :: 4 - Beta
Classifier: Intended Audience :: Developers
Classifier: Programming Language :: Python :: 3
Classifier: Programming Language :: Python :: 3.8
Classifier: Programming Language :: Python :: 3.9
Classifier: Programming Language :: Python :: 3.10
Classifier: Programming Language :: Python :: 3.11
Classifier: Programming Language :: Python :: 3.12
Classifier: Programming Language :: Python :: 3.13
Classifier: Topic :: Software Development :: Debuggers
Classifier: Topic :: Software Development :: Libraries :: Python Modules
Requires-Python: >=3.8
License-File: LICENSE
Requires-Dist: pygments
Requires-Dist: colorama
Requires-Dist: executing
Requires-Dist: asttokens
Provides-Extra: dev
Requires-Dist: pytest>=6.0; extra == "dev"
Requires-Dist: pytest-cov; extra == "dev"
Requires-Dist: black; extra == "dev"
Requires-Dist: isort; extra == "dev"
Requires-Dist: mypy; extra == "dev"
Requires-Dist: flake8; extra == "dev"
Dynamic: license-file
